decorator_libs/__init__.py
decorator_libs/black_technology_decorators.py
decorator_libs/common_decorators.py
decorator_libs/function_timeout_decorators.py
decorator_libs-1.5.dist-info/METADATA
decorator_libs-1.5.dist-info/WHEEL
decorator_libs-1.5.dist-info/top_level.txt
decorator_libs-1.5.dist-info/RECORD
