Metadata-Version: 2.1
Name: decorator-libs
Version: 1.5
Summary: all kinds of decorators
Home-page: 
Author: bfzs
Author-email: m13148804508@163.com
Maintainer: ydf
Maintainer-email: m13148804508@163.com
License: BSD License
Keywords: pysnooper,decorator
Platform: all
Classifier: Development Status :: 4 - Beta
Classifier: Operating System :: OS Independent
Classifier: Intended Audience :: Developers
Classifier: License :: OSI Approved :: BSD License
Classifier: Programming Language :: Python
Classifier: Programming Language :: Python :: Implementation
Classifier: Programming Language :: Python :: 3.6
Classifier: Topic :: Software Development :: Libraries
Requires-Dist: nb-log
Requires-Dist: pysnooper
Requires-Dist: pysnooper-click-able
Requires-Dist: tomorrow3
Requires-Dist: flask
